structlogx/__init__.py
structlogx-0.1.3.dist-info/licenses/LICENSE
structlogx-0.1.3.dist-info/METADATA
structlogx-0.1.3.dist-info/WHEEL
structlogx-0.1.3.dist-info/top_level.txt
structlogx-0.1.3.dist-info/RECORD
