Metadata-Version: 2.4
Name: structlogx
Version: 0.1.3
Summary: A simple Python logging package
Home-page: https://github.com/Lethonium/structlogx
Author: lethonium
Author-email: info@lethonium.com
License: MIT
Classifier: Programming Language :: Python :: 3
Classifier: Operating System :: OS Independent
Requires-Python: >=3.6
License-File: LICENSE
Requires-Dist: python-json-logger
Dynamic: author
Dynamic: author-email
Dynamic: classifier
Dynamic: description
Dynamic: description-content-type
Dynamic: home-page
Dynamic: license
Dynamic: license-file
Dynamic: requires-dist
Dynamic: requires-python
Dynamic: summary
